biomarker_survival/__init__.py
biomarker_survival/analysis.py
biomarker_survival/mutation_base.py
biomarker_survival/pancan.py
biomarker_survival/tcga_cdr_utilities.py
biomarker_survival/utilities.py
biomarker_survival-0.2.4.dist-info/LICENSE
biomarker_survival-0.2.4.dist-info/METADATA
biomarker_survival-0.2.4.dist-info/WHEEL
biomarker_survival-0.2.4.dist-info/top_level.txt
biomarker_survival-0.2.4.dist-info/RECORD
