Metadata-Version: 2.1
Name: biomarker-survival
Version: 0.2.4
Summary: Utilities for performing biomarker survival analyses
Home-page: http://github.com/joansmith/biomarker-survival
Author: Joan Smith
Author-email: joans@alum.mit.edu
License: MIT
Platform: UNKNOWN
License-File: LICENSE
Requires-Dist: pandas (>=0.25.1)
Requires-Dist: rpy2 (==3.4.5)
Requires-Dist: matplotlib
Requires-Dist: scipy (>=1.3.1)
Requires-Dist: tzlocal
Requires-Dist: openpyxl
